pyupbit_for_devs/LICENSE
pyupbit_for_devs/__init__.py
pyupbit_for_devs/exchange_api.py
pyupbit_for_devs/quotation_api.py
pyupbit_for_devs/request_api.py
pyupbit_for_devs/trade_utils.py
pyupbit_for_devs/websocket_api.py
pyupbit_for_devs-0.1.3.dist-info/LICENSE
pyupbit_for_devs-0.1.3.dist-info/METADATA
pyupbit_for_devs-0.1.3.dist-info/WHEEL
pyupbit_for_devs-0.1.3.dist-info/top_level.txt
pyupbit_for_devs-0.1.3.dist-info/RECORD
