Metadata-Version: 2.1
Name: pyupbit-for-devs
Version: 0.1.3
Summary: Augmented pyupbit for Developers
Home-page: https://github.com/DSsoli/pyupbit-for-devs.git
Author: Sanghoon Lee (DSsoli)
Author-email: solisoli3197@gmail.com
Classifier: Programming Language :: Python :: 3
Classifier: License :: OSI Approved :: Apache Software License
Classifier: Operating System :: OS Independent
Requires-Python: >=3.6
License-File: LICENSE
Requires-Dist: pyjwt (>=2.0.0)
Requires-Dist: pandas
Requires-Dist: requests
Requires-Dist: websockets
